geok/__init__.py
geok/core.py
geok-0.1.0.dist-info/LICENSE
geok-0.1.0.dist-info/WHEEL
geok-0.1.0.dist-info/METADATA
geok-0.1.0.dist-info/RECORD
